wedne/__init__.py
wedne/__main__.py
wedne/client/__init__.py
wedne/client/__main__.py
wedne/client/consts.py
wedne/client/shared_commands.py
wedne/client/telegram.py
wedne/client/watcher.py
wedne/commands.py
wedne/commands_test.py
wedne/server/__init__.py
wedne/server/__main__.py
wedne/server/api/__init__.py
wedne/server/api/stats.py
wedne/server/api/visits.py
wedne/server/db.py
wedne/server/gunicorn.py
wedne/server/settings.py
wedne/server/tasks.py
wedne/utils.py
wedne/utils_test.py
wedne-1.2.0.dist-info/LICENSE.txt
wedne-1.2.0.dist-info/METADATA
wedne-1.2.0.dist-info/WHEEL
wedne-1.2.0.dist-info/RECORD
