Metadata-Version: 2.1
Name: wedne
Version: 1.2.0
Summary: Координируем строительство башни
Home-page: https://github.com/igoose1/wedne
License: BSD-3-Clause
Author: Oskar Sharipov
Requires-Python: >=3.10,<4.0
Classifier: License :: OSI Approved :: BSD License
Classifier: Programming Language :: Python :: 3
Classifier: Programming Language :: Python :: 3.10
Classifier: Programming Language :: Python :: 3.11
Classifier: Programming Language :: Python :: 3.12
Requires-Dist: aiorun (>=2023.7.2,<2024.0.0)
Requires-Dist: fire (>=0.5.0,<0.6.0)
Requires-Dist: httpx (>=0.24.1,<0.25.0)
Requires-Dist: pydantic-settings (>=2.0.2,<3.0.0)
Requires-Dist: pydantic[dotenv] (>=2.1.0,<3.0.0)
Requires-Dist: pytz (>=2023.3,<2024.0)
Requires-Dist: telethon (>=1.28.5,<2.0.0)
Project-URL: Repository, https://github.com/igoose1/wedne
